selfmind/__init__.py
selfmind-1.0.0.dist-info/METADATA
selfmind-1.0.0.dist-info/WHEEL
selfmind-1.0.0.dist-info/top_level.txt
selfmind-1.0.0.dist-info/RECORD
