Metadata-Version: 2.4
Name: selfmind
Version: 1.0.0
Summary: The Smart Code Memory library for high performance and error prediction
Home-page: https://t.me/QP4RM
Author: MERO
Author-email: MERO <mero@example.com>
License: MIT
Project-URL: Homepage, https://t.me/QP4RM
Classifier: Programming Language :: Python :: 3
Classifier: License :: OSI Approved :: MIT License
Classifier: Operating System :: OS Independent
Requires-Python: >=3.5
Requires-Dist: psutil
Requires-Dist: requests
Dynamic: author
Dynamic: home-page
Dynamic: requires-python
